stactools/planet/__init__.py
stactools/planet/commands.py
stactools/planet/constants.py
stactools/planet/orders.py
stactools/planet/planet_item.py
stactools_planet-0.2.0.dist-info/LICENSE
stactools_planet-0.2.0.dist-info/METADATA
stactools_planet-0.2.0.dist-info/WHEEL
stactools_planet-0.2.0.dist-info/top_level.txt
stactools_planet-0.2.0.dist-info/RECORD
